vnpy_extra_tb/__init__.py
vnpy_extra_tb/ams.py
vnpy_extra_tb/signals.py
vnpy_extra_tb-0.2.20210916.0.dist-info/LICENSE
vnpy_extra_tb-0.2.20210916.0.dist-info/METADATA
vnpy_extra_tb-0.2.20210916.0.dist-info/WHEEL
vnpy_extra_tb-0.2.20210916.0.dist-info/top_level.txt
vnpy_extra_tb-0.2.20210916.0.dist-info/RECORD
